numbsql/__init__.py
numbsql/aggregate.py
numbsql/exceptions.py
numbsql/numbaext.py
numbsql/scalar.py
numbsql/sqlite.py
numbsql/tests/conftest.py
numbsql/tests/test_aggregate.py
numbsql/tests/test_numbaext.py
numbsql/tests/test_ref_count_perf.py
numbsql/tests/test_scalar.py
numbsql/tests/test_version.py
numbsql-8.1.0.dist-info/METADATA
numbsql-8.1.0.dist-info/WHEEL
numbsql-8.1.0.dist-info/licenses/LICENSE
numbsql-8.1.0.dist-info/RECORD
