Metadata-Version: 2.4
Name: numbsql
Version: 8.1.0
Summary: JITted SQLite user-defined scalar and aggregate functions
Project-URL: Homepage, https://github.com/cpcloud/numbsql
Project-URL: Repository, https://github.com/cpcloud/numbsql
Project-URL: Issues, https://github.com/cpcloud/numbsql/issues
Author-email: Phillip Cloud <417981+cpcloud@users.noreply.github.com>
Maintainer-email: Phillip Cloud <417981+cpcloud@users.noreply.github.com>
License-Expression: Apache-2.0
License-File: LICENSE
Classifier: Intended Audience :: Developers
Classifier: Programming Language :: Python :: 3.10
Classifier: Programming Language :: Python :: 3.11
Classifier: Programming Language :: Python :: 3.12
Classifier: Programming Language :: Python :: 3.13
Requires-Python: <4,>=3.10
Requires-Dist: llvmlite<0.45,>=0.36
Requires-Dist: numba<0.62,>=0.53
